rom24/__init__.py
rom24/affects.py
rom24/auth.py
rom24/bit.py
rom24/comm.py
rom24/const.py
rom24/data_loader.py
rom24/db.py
rom24/effects.py
rom24/environment.py
rom24/equipment.py
rom24/fight.py
rom24/game_utils.py
rom24/handler_ch.py
rom24/handler_game.py
rom24/handler_item.py
rom24/handler_magic.py
rom24/handler_npc.py
rom24/handler_pc.py
rom24/handler_room.py
rom24/hotfix.py
rom24/immortal.py
rom24/instance.py
rom24/interp.py
rom24/inventory.py
rom24/item_flags.py
rom24/living.py
rom24/magic.py
rom24/merc.py
rom24/nanny.py
rom24/object_creator.py
rom24/physical.py
rom24/pyom.py
rom24/pyprogs.py
rom24/save.py
rom24/settings.py
rom24/shell.py
rom24/shop_utils.py
rom24/skills.py
rom24/special.py
rom24/state_checks.py
rom24/sys_utils.py
rom24/tables.py
rom24/type_bypass.py
rom24/update.py
rom24/world_classes.py
rom24/commands/__init__.py
rom24/commands/do_advance.py
rom24/commands/do_affects.py
rom24/commands/do_afk.py
rom24/commands/do_alias.py
rom24/commands/do_answer.py
rom24/commands/do_apickle.py
rom24/commands/do_areas.py
rom24/commands/do_auction.py
rom24/commands/do_authenticator.py
rom24/commands/do_autoassist.py
rom24/commands/do_autoexit.py
rom24/commands/do_autogold.py
rom24/commands/do_autolist.py
rom24/commands/do_autoloot.py
rom24/commands/do_autosac.py
rom24/commands/do_autosplit.py
rom24/commands/do_backstab.py
rom24/commands/do_bamfin.py
rom24/commands/do_bamfout.py
rom24/commands/do_bash.py
rom24/commands/do_berserk.py
rom24/commands/do_brandish.py
rom24/commands/do_brief.py
rom24/commands/do_bug.py
rom24/commands/do_buy.py
rom24/commands/do_cast.py
rom24/commands/do_channels.py
rom24/commands/do_clantalk.py
rom24/commands/do_clone.py
rom24/commands/do_close.py
rom24/commands/do_combine.py
rom24/commands/do_commands.py
rom24/commands/do_compact.py
rom24/commands/do_compare.py
rom24/commands/do_consider.py
rom24/commands/do_count.py
rom24/commands/do_deaf.py
rom24/commands/do_debug.py
rom24/commands/do_delete.py
rom24/commands/do_deny.py
rom24-0.0.1a2.dist-info/METADATA
rom24-0.0.1a2.dist-info/WHEEL
rom24-0.0.1a2.dist-info/entry_points.txt
rom24-0.0.1a2.dist-info/top_level.txt
rom24-0.0.1a2.dist-info/RECORD
