Metadata-Version: 2.1
Name: rom24
Version: 0.0.1a2
Summary: Attempt at properly packaging rom24 python.
Home-page: UNKNOWN
Author: Micheal Taylor
Author-email: bubthegreat@gmail.com
License: UNKNOWN
Platform: UNKNOWN
Requires-Python: >=3.6.6
Requires-Dist: black
Requires-Dist: ipdb
Requires-Dist: mypy
Requires-Dist: pre-commit
Requires-Dist: psutil
Requires-Dist: pytest
